{
  "$schema": "https://ui.shadcn.com/schema/registry-item.json",
  "name": "media-player",
  "title": "Media Player",
  "description": "A media player component for audio and video files",
  "dependencies": ["mediabunny"],
  "registryDependencies": ["button", "dialog", "item", "card", "dropdown-menu", "slider"],
  "files": [
    {
      "path": "src/components/media-player/index.ts",
      "content": "export { default as Player } from './player'\n",
      "type": "registry:file",
      "target": "@components/media-player/index.ts"
    },
    {
      "path": "src/components/media-player/info-modal.tsx",
      "content": "import {\n  Dialog,\n  DialogContent,\n  DialogDescription,\n  DialogHeader,\n  DialogTitle,\n  DialogTrigger\n} from '@/components/ui/dialog'\nimport { Item, ItemContent, ItemDescription, ItemTitle } from '@/components/ui/item'\nimport { getTracksData, TrackData } from './mediabunny'\nimport { memo, useEffect, useState } from 'react'\nimport { formatBitrate, formatBytes, formatDuration, truncateTo2Decimals } from './utils'\nimport { usePlayerStaticContext } from './provider'\n\nfunction TrackInfoField({ title, value }: { title: string; value: React.ReactNode }) {\n  return (\n    <Item>\n      <ItemContent>\n        <ItemTitle>{title}</ItemTitle>\n        <ItemDescription>{value}</ItemDescription>\n      </ItemContent>\n    </Item>\n  )\n}\n\nfunction getTrackInfoFields(track: TrackData) {\n  const fields: { title: string; value: React.ReactNode }[] = [\n    {\n      title: 'Average bitrate',\n      value: track.averageBitrate ? formatBitrate(track.averageBitrate) : 'N/A'\n    },\n    { title: 'Codec', value: track.codec ?? 'N/A' },\n    { title: 'Codec string', value: track.codecParamString ?? 'N/A' },\n    { title: 'Language', value: track.lang ?? 'N/A' }\n  ]\n\n  if (track.isVideo) {\n    fields.push(\n      {\n        title: 'Frame rate',\n        value: track.frameRate ? truncateTo2Decimals(track.frameRate) : 'N/A'\n      },\n      { title: 'Coded height', value: track.codedHeight ?? 'N/A' },\n      { title: 'Coded width', value: track.codedWidth ?? 'N/A' },\n      { title: 'Display height', value: track.displayHeight ?? 'N/A' },\n      { title: 'Display width', value: track.displayWidth ?? 'N/A' }\n    )\n  }\n\n  if (track.isAudio) {\n    fields.push(\n      { title: 'Sample rate', value: track.sampleRate ?? 'N/A' },\n      { title: 'Channels', value: track.channels ?? 'N/A' }\n    )\n  }\n\n  return fields\n}\n\ntype InfoModalProps = {\n  children?: React.ReactNode\n  open?: boolean\n  onOpenChange?: (open: boolean) => void\n}\n\nexport const InfoModal = memo(function InfoModal({ children, open, onOpenChange }: InfoModalProps) {\n  const { file, fileData } = usePlayerStaticContext()\n  const [tracksData, setTracksData] = useState<TrackData[]>([])\n\n  useEffect(() => {\n    getTracksData(file).then((tracksData) => {\n      setTracksData(tracksData)\n    })\n  }, [file])\n\n  const hoverCardContentMap = {\n    'Last modified': new Date(file.lastModified).toLocaleDateString(),\n    Size: formatBytes(file.size),\n    Format: fileData?.format.name,\n    'MIME Type': fileData?.format.mimeType,\n    Duration: fileData?.duration ? formatDuration(fileData.duration) : 'N/A',\n    Artist: fileData?.metadataTags.artist,\n    Album: fileData?.metadataTags.album,\n    'Total tracks': fileData?.metadataTags.tracksTotal,\n    Genre: fileData?.metadataTags.genre\n  }\n\n  return (\n    <Dialog open={open} onOpenChange={onOpenChange}>\n      {children ? <DialogTrigger asChild>{children}</DialogTrigger> : null}\n      <DialogContent>\n        <DialogHeader>\n          <DialogTitle>Info</DialogTitle>\n          <DialogDescription>Metadata about the file</DialogDescription>\n        </DialogHeader>\n        <div className=\"-mx-4 no-scrollbar max-h-[50vh] overflow-y-auto px-4\">\n          <div className=\"grid grid-cols-2 gap-2\">\n            {Object.entries(hoverCardContentMap).map(\n              ([key, value]) =>\n                value && (\n                  <Item variant=\"default\" size=\"xs\" key={key}>\n                    <ItemContent>\n                      <ItemTitle className=\"font-semibold text-xs\">{key}</ItemTitle>\n                      <ItemDescription className=\"text-xs\">{value}</ItemDescription>\n                    </ItemContent>\n                  </Item>\n                )\n            )}\n          </div>\n          <Item size=\"xs\" className=\"p-0\">\n            <ItemContent>\n              <div className=\"space-y-4\">\n                {tracksData.map((track) => (\n                  <Item\n                    key={track.id}\n                    variant=\"default\"\n                    className='**:data-[slot=\"item-title\"]:text-xs **:data-[slot=\"item-description\"]:text-xs bg-muted'\n                  >\n                    <ItemContent>\n                      <ItemTitle className=\"capitalize bg-primary text-primary-foreground p-1 px-2 rounded-full text-[10px]!\">\n                        {track.type}\n                      </ItemTitle>\n                      <div className=\"grid grid-cols-2 gap-2\">\n                        {getTrackInfoFields(track).map((field) => (\n                          <TrackInfoField\n                            key={field.title}\n                            title={field.title}\n                            value={field.value}\n                          />\n                        ))}\n                      </div>\n                    </ItemContent>\n                  </Item>\n                ))}\n              </div>\n            </ItemContent>\n          </Item>\n        </div>\n      </DialogContent>\n    </Dialog>\n  )\n})\n",
      "type": "registry:component",
      "target": "@components/media-player/info-modal.tsx"
    },
    {
      "path": "src/components/media-player/mediabunny.ts",
      "content": "'use client'\n\nimport {\n  ALL_FORMATS,\n  BlobSource,\n  Input,\n  InputAudioTrack,\n  InputTrack,\n  MetadataTags,\n  Rotation\n} from 'mediabunny'\n\nexport type InputFileData = {\n  audioTracks: InputAudioTrack[]\n  duration: number\n  format: {\n    name: string\n    mimeType: string\n  }\n  metadataTags: MetadataTags\n  mimeType: string\n  size: number | null\n}\n\nexport type TrackData = Awaited<ReturnType<typeof getTrackData>> & {\n  codedHeight?: number\n  codedWidth?: number\n  colorSpace?: VideoColorSpaceInit\n  displayHeight?: number\n  displayWidth?: number\n  rotation?: Rotation\n  frameRate?: number\n  sampleRate?: number\n  channels?: number\n}\n\nfunction getInput(file: File) {\n  return new Input({\n    formats: ALL_FORMATS,\n    source: new BlobSource(file)\n  })\n}\n\nexport async function getFileData(file: File): Promise<InputFileData> {\n  const input = getInput(file)\n\n  let data = {}\n\n  const [audioTracks, duration, format, metadataTags, mimeType, size] = await Promise.all([\n    input.getAudioTracks(),\n    input.getDurationFromMetadata(),\n    input.getFormat(),\n    input.getMetadataTags(),\n    input.getMimeType(),\n    input.source.getSizeOrNull()\n  ])\n\n  data = {\n    audioTracks,\n    duration,\n    format: { name: format.name, mimeType: format.mimeType },\n    metadataTags,\n    mimeType,\n    size\n  }\n\n  return data as InputFileData\n}\n\nexport async function getTrackData(track: InputTrack) {\n  const codec = await track.getCodec()\n  const codecParamString = await track.getCodecParameterString()\n  const disposition = await track.getDisposition()\n  const duration = await track.getDurationFromMetadata()\n  const lang = await track.getLanguageCode()\n  const isAudio = track.isAudioTrack()\n  const isVideo = track.isVideoTrack()\n  const stats = await track.computePacketStats(100)\n  const averageBitrate = stats.averageBitrate\n  let trackData = {\n    id: track.id,\n    type: track.type,\n    averageBitrate,\n    codec,\n    codecParamString,\n    disposition,\n    duration,\n    lang,\n    isAudio,\n    isVideo\n  }\n\n  if (track.isVideoTrack()) {\n    const codedHeight = await track.getCodedHeight()\n    const codedWidth = await track.getCodedWidth()\n    const colorSpace = await track.getColorSpace()\n    const displayHeight = await track.getDisplayHeight()\n    const displayWidth = await track.getDisplayWidth()\n    const rotation = await track.getRotation()\n    const frameRate = stats.averagePacketRate\n    const videoData = {\n      codedHeight,\n      codedWidth,\n      colorSpace,\n      displayHeight,\n      displayWidth,\n      rotation,\n      frameRate,\n      averageBitrate\n    }\n\n    trackData = { ...trackData, ...videoData }\n  } else if (track.isAudioTrack()) {\n    const sampleRate = await track.getSampleRate()\n    const channels = await track.getNumberOfChannels()\n    const audioData = { sampleRate, channels }\n\n    trackData = { ...trackData, ...audioData }\n  }\n\n  return trackData\n}\n\nexport async function getTracksData(file: File) {\n  const input = getInput(file)\n  const tracks = await input.getTracks()\n\n  const tracksData = []\n\n  for (const track of tracks) {\n    const trackData = await getTrackData(track)\n    tracksData.push(trackData)\n  }\n\n  return tracksData\n}\n",
      "type": "registry:file",
      "target": "@components/media-player/mediabunny.ts"
    },
    {
      "path": "src/components/media-player/player.tsx",
      "content": "'use client'\n\nimport {\n  EllipsisVertical,\n  Image as ImageIcon,\n  Info,\n  Maximize,\n  Music,\n  Pause,\n  Play,\n  Volume2,\n  VolumeX\n} from 'lucide-react'\nimport { Card, CardContent, CardFooter } from '@/components/ui/card'\nimport { memo, useState } from 'react'\nimport { Slider } from '@/components/ui/slider'\nimport { Button } from '@/components/ui/button'\nimport { cn } from '@/lib/utils'\nimport { formatDuration } from './utils'\nimport { PlayerProvider, usePlayerStaticContext, usePlayerPlaybackContext } from './provider'\nimport { InfoModal } from './info-modal'\nimport {\n  DropdownMenu,\n  DropdownMenuContent,\n  DropdownMenuGroup,\n  DropdownMenuItem,\n  DropdownMenuTrigger\n} from '@/components/ui/dropdown-menu'\n\ntype PlayerProps = {\n  file: File\n  showHTMLControls?: boolean\n}\n\nconst Player = ({ file, showHTMLControls }: PlayerProps) => {\n  return (\n    <PlayerProvider file={file} showHTMLControls={showHTMLControls}>\n      <PlayerMain />\n    </PlayerProvider>\n  )\n}\n\nconst PlayerMain = () => {\n  const { fileData } = usePlayerStaticContext()\n\n  return (\n    <Card className=\"w-86 md:w-120 h-71 md:h-90 max-w-full gap-0 p-0 relative overflow-hidden\">\n      {!fileData ? (\n        <div className=\"absolute inset-0 bg-muted animate-pulse\" />\n      ) : (\n        <>\n          <Poster />\n          <Video />\n          <PlayerFooter />\n        </>\n      )}\n    </Card>\n  )\n}\n\nconst Poster = memo(function Poster() {\n  const { posterUrl } = usePlayerStaticContext()\n\n  if (!posterUrl) return null\n\n  return (\n    <img\n      data-posterimage\n      width={100}\n      height={100}\n      src={posterUrl}\n      alt=\"Poster\"\n      className=\"absolute inset-0 h-full w-full\"\n    />\n  )\n})\n\nconst Video = memo(function Video() {\n  const { videoRef, showHTMLControls, posterUrl, videoUrl, setIsPlaying, type, playPause } =\n    usePlayerStaticContext()\n\n  return (\n    <CardContent className=\"p-0 relative aspect-video\" onClick={playPause}>\n      {type === 'audio' && !posterUrl && (\n        <div className=\"absolute inset-0 flex items-center justify-center bg-linear-to-b from-primary/10 to-transparent\">\n          <Music className=\"size-14 text-primary\" />\n        </div>\n      )}\n      <video\n        data-video\n        ref={videoRef}\n        controls={showHTMLControls}\n        poster={posterUrl}\n        src={videoUrl}\n        className=\"w-full h-full\"\n        onPlay={() => setIsPlaying(true)}\n        onPause={() => setIsPlaying(false)}\n        onEnded={() => setIsPlaying(false)}\n      />\n    </CardContent>\n  )\n})\n\nconst PlayerFooter = memo(function PlayerFooter() {\n  const { posterUrl } = usePlayerStaticContext()\n\n  return (\n    <CardFooter\n      className={cn(\n        'flex min-w-0 w-full flex-col gap-2 overflow-hidden border-none relative',\n        posterUrl ? 'bg-black/30 backdrop-blur-md' : 'bg-background',\n        !posterUrl ? '**:data-time:text-foreground' : '**:data-time:text-white',\n        '**:data-playpause:text-primary-foreground **:data-playpause:bg-primary/80',\n        '**:data-controls-right:text-primary-foreground **:data-controls-right:bg-primary/80',\n        !posterUrl ? '**:data-filename:text-foreground' : '**:data-filename:text-white',\n        \"**:data-[slot='slider-track']:bg-primary/30 **:data-[slot='slider-track']:cursor-pointer\",\n        \"**:data-[slot='slider-range']:bg-primary/80\"\n      )}\n    >\n      <Controls />\n      <ProgressBar />\n      <FileName />\n    </CardFooter>\n  )\n})\n\nconst Controls = () => {\n  const { playPause, handleMute, handleCapture, type } = usePlayerStaticContext()\n  const { currentTime, duration, isPlaying, isMuted } = usePlayerPlaybackContext()\n\n  const rightControls = [\n    {\n      id: 'mute',\n      icon: isMuted ? <VolumeX className=\"size-3\" /> : <Volume2 className=\"size-3\" />,\n      onClick: handleMute\n    },\n    {\n      id: 'capture',\n      icon: <ImageIcon className=\"size-3\" />,\n      onClick: handleCapture\n    }\n  ]\n\n  return (\n    <div className=\"text-xs font-sans w-full grid grid-cols-3\">\n      <span data-time className=\"flex items-center\">\n        {formatDuration(currentTime)} / {formatDuration(duration)}\n      </span>\n      <span className=\"flex items-center justify-center\">\n        <Button data-playpause size=\"icon-xs\" onClick={playPause}>\n          {isPlaying ? <Pause className=\"size-3\" /> : <Play className=\"size-3\" />}\n        </Button>\n      </span>\n      <div className=\"flex items-center justify-end gap-2\">\n        {rightControls.map((control) => {\n          if (type === 'audio' && control.id === 'capture') {\n            return null\n          }\n          return (\n            <Button key={control.id} data-controls-right size=\"icon-xs\" onClick={control.onClick}>\n              {control.icon}\n            </Button>\n          )\n        })}\n        <MoreControls>\n          <Button data-controls-right size=\"icon-xs\">\n            <EllipsisVertical className=\"size-3\" />\n          </Button>\n        </MoreControls>\n      </div>\n    </div>\n  )\n}\n\nconst MoreControls = ({ children }: { children: React.ReactNode }) => {\n  const { handleMaximize } = usePlayerStaticContext()\n  const [infoOpen, setInfoOpen] = useState(false)\n\n  const moreControls = [\n    {\n      id: 'info',\n      icon: <Info className=\"size-3\" />,\n      label: 'Info'\n    },\n    {\n      id: 'maximize',\n      icon: <Maximize className=\"size-3\" />,\n      onClick: handleMaximize,\n      label: 'Maximize'\n    }\n  ]\n\n  return (\n    <>\n      <DropdownMenu>\n        <DropdownMenuTrigger asChild>{children}</DropdownMenuTrigger>\n        <DropdownMenuContent side=\"top\" align=\"end\" className=\"p-2\">\n          <DropdownMenuGroup className=\"space-y-1\">\n            {moreControls.map((control) => {\n              if (control.id === 'info') {\n                return (\n                  <DropdownMenuItem\n                    key={control.id}\n                    className=\"text-xs cursor-pointer\"\n                    onSelect={() => setInfoOpen(true)}\n                  >\n                    {control.icon} {control.label}\n                  </DropdownMenuItem>\n                )\n              }\n              return (\n                <DropdownMenuItem\n                  key={control.id}\n                  className=\"text-xs cursor-pointer\"\n                  onClick={control.onClick}\n                >\n                  {control.icon} {control.label}\n                </DropdownMenuItem>\n              )\n            })}\n          </DropdownMenuGroup>\n        </DropdownMenuContent>\n      </DropdownMenu>\n      <InfoModal open={infoOpen} onOpenChange={setInfoOpen} />\n    </>\n  )\n}\n\nconst ProgressBar = () => {\n  const { sliderOnValueChange } = usePlayerStaticContext()\n  const { progress } = usePlayerPlaybackContext()\n\n  return (\n    <Slider\n      value={[progress]}\n      max={100}\n      onValueChange={sliderOnValueChange}\n      className=\"flex-1 w-full\"\n    />\n  )\n}\n\nconst FileName = memo(function FileName() {\n  const { fileData, file } = usePlayerStaticContext()\n\n  const fileName = fileData?.metadataTags.title || file.name\n\n  return (\n    <span data-filename className=\"min-w-0 w-full truncate text-xs text-center\" title={fileName}>\n      {fileName}\n    </span>\n  )\n})\n\nexport default Player\n",
      "type": "registry:component",
      "target": "@components/media-player/player.tsx"
    },
    {
      "path": "src/components/media-player/provider.tsx",
      "content": "import { getFileData, InputFileData } from './mediabunny'\nimport { createContext, useCallback, useContext, useEffect, useMemo, useRef, useState } from 'react'\nimport { getType } from './utils'\n\ntype PlaybackState = {\n  progress: number\n  duration: number\n  currentTime: number\n  isPlaying: boolean\n  isMuted: boolean\n}\n\ntype PlayerStaticContextType = {\n  file: File\n  fileData: InputFileData | null\n  videoRef: React.RefObject<HTMLVideoElement | null>\n  posterUrl: string | undefined\n  videoUrl: string | undefined\n  showHTMLControls: boolean | undefined\n  setIsPlaying: (isPlaying: boolean) => void\n  setIsMuted: (isMuted: boolean) => void\n  sliderOnValueChange: (value: number[]) => void\n  playPause: () => void\n  handleMute: () => void\n  handleMaximize: () => void\n  handleCapture: () => void\n  type: 'video' | 'audio' | 'unknown'\n}\n\nconst PlayerStaticContext = createContext<PlayerStaticContextType | undefined>(undefined)\n\nconst PlayerPlaybackContext = createContext<PlaybackState | undefined>(undefined)\n\nexport const PlayerProvider = ({\n  children,\n  file,\n  showHTMLControls\n}: {\n  children: React.ReactNode\n  file: File\n  showHTMLControls: boolean | undefined\n}) => {\n  const [fileData, setFileData] = useState<InputFileData | null>(null)\n  const videoRef = useRef<HTMLVideoElement | null>(null)\n  const [playback, setPlayback] = useState<PlaybackState>({\n    progress: 0,\n    duration: 0,\n    currentTime: 0,\n    isPlaying: false,\n    isMuted: false\n  })\n  const [videoUrl, setVideoUrl] = useState<string>()\n  const [posterUrl, setPosterUrl] = useState<string>()\n  const type = getType(file)\n\n  useEffect(() => {\n    const url = URL.createObjectURL(file)\n    setVideoUrl(url)\n\n    return () => URL.revokeObjectURL(url)\n  }, [file])\n\n  const image = fileData?.metadataTags.images?.[0]\n\n  useEffect(() => {\n    if (!image) {\n      setPosterUrl(undefined)\n      return\n    }\n\n    const url = URL.createObjectURL(\n      new Blob([new Uint8Array(image.data)], {\n        type: image.mimeType\n      })\n    )\n\n    setPosterUrl(url)\n\n    return () => URL.revokeObjectURL(url)\n  }, [image])\n\n  useEffect(() => {\n    getFileData(file).then(setFileData)\n  }, [file])\n\n  useEffect(() => {\n    const video = videoRef.current\n    if (!video) return\n    const syncDuration = () => {\n      if (Number.isFinite(video.duration)) {\n        setPlayback((prev) => ({ ...prev, duration: video.duration }))\n      }\n    }\n    const handleTimeUpdate = () => {\n      setPlayback((prev) => ({\n        ...prev,\n        currentTime: video.currentTime,\n        progress: Number.isFinite(video.duration)\n          ? (video.currentTime / video.duration) * 100\n          : prev.progress\n      }))\n    }\n    syncDuration()\n    video.addEventListener('loadedmetadata', syncDuration)\n    video.addEventListener('durationchange', syncDuration)\n    video.addEventListener('timeupdate', handleTimeUpdate)\n    return () => {\n      video.removeEventListener('loadedmetadata', syncDuration)\n      video.removeEventListener('durationchange', syncDuration)\n      video.removeEventListener('timeupdate', handleTimeUpdate)\n    }\n  }, [fileData])\n\n  const setIsPlaying = useCallback((isPlaying: boolean) => {\n    setPlayback((prev) => ({ ...prev, isPlaying }))\n  }, [])\n\n  const setIsMuted = useCallback((isMuted: boolean) => {\n    setPlayback((prev) => ({ ...prev, isMuted }))\n  }, [])\n\n  const sliderOnValueChange = useCallback((val: number[]) => {\n    setPlayback((prev) => ({ ...prev, progress: val[0] }))\n    const video = videoRef.current\n    if (!video) return\n    video.currentTime = (val[0] / 100) * video.duration\n  }, [])\n\n  const playPause = useCallback(() => {\n    const video = videoRef.current\n    if (!video) return\n    if (video.paused) {\n      void video.play()\n    } else {\n      video.pause()\n    }\n  }, [])\n\n  const handleMute = useCallback(() => {\n    const video = videoRef.current\n    if (!video) return\n    video.muted = !video.muted\n    setPlayback((prev) => ({ ...prev, isMuted: video.muted }))\n  }, [])\n\n  const handleMaximize = useCallback(() => {\n    videoRef.current?.requestFullscreen()\n  }, [])\n\n  const handleCapture = useCallback(() => {\n    const video = videoRef.current\n    if (!video) return\n    video.pause()\n    const canvas = document.createElement('canvas')\n    canvas.width = video.videoWidth\n    canvas.height = video.videoHeight\n    canvas.getContext('2d')?.drawImage(video, 0, 0)\n    const image = canvas.toDataURL()\n    const link = document.createElement('a')\n    link.href = image\n    link.download = 'frame_' + file.name.split('.').slice(0, -1).join('.') + '.png'\n    link.target = '_blank'\n    link.click()\n    link.remove()\n  }, [file.name])\n\n  const staticValue = useMemo<PlayerStaticContextType>(() => {\n    return {\n      file,\n      fileData,\n      videoRef,\n      showHTMLControls,\n      posterUrl,\n      videoUrl,\n      setIsPlaying,\n      setIsMuted,\n      sliderOnValueChange,\n      playPause,\n      handleMute,\n      handleMaximize,\n      handleCapture,\n      type\n    }\n  }, [\n    file,\n    fileData,\n    showHTMLControls,\n    posterUrl,\n    videoUrl,\n    setIsPlaying,\n    setIsMuted,\n    sliderOnValueChange,\n    playPause,\n    handleMute,\n    handleMaximize,\n    handleCapture,\n    type\n  ])\n\n  return (\n    <PlayerStaticContext.Provider value={staticValue}>\n      <PlayerPlaybackContext.Provider value={playback}>{children}</PlayerPlaybackContext.Provider>\n    </PlayerStaticContext.Provider>\n  )\n}\n\nexport const usePlayerStaticContext = () => {\n  const context = useContext(PlayerStaticContext)\n  if (!context) {\n    throw new Error('usePlayerStaticContext must be used within a PlayerProvider')\n  }\n  return context\n}\n\nexport const usePlayerPlaybackContext = () => {\n  const context = useContext(PlayerPlaybackContext)\n  if (!context) {\n    throw new Error('usePlayerPlaybackContext must be used within a PlayerProvider')\n  }\n  return context\n}\n",
      "type": "registry:component",
      "target": "@components/media-player/provider.tsx"
    },
    {
      "path": "src/components/media-player/utils.ts",
      "content": "export function formatBytes(bytes: number) {\n  const sizes = ['B', 'KB', 'MB', 'GB']\n  const i = Math.floor(Math.log(bytes) / Math.log(1024))\n  return (bytes / Math.pow(1024, i)).toFixed(2) + ' ' + sizes[i]\n}\n\nexport function formatDuration(duration: number): string {\n  const totalSeconds = Math.floor(duration)\n\n  const hours = Math.floor(totalSeconds / 3600)\n  const minutes = Math.floor((totalSeconds % 3600) / 60)\n  const seconds = totalSeconds % 60\n\n  if (hours > 0) {\n    return `${hours.toString().padStart(2, '0')}:${minutes\n      .toString()\n      .padStart(2, '0')}:${seconds.toString().padStart(2, '0')}`\n  }\n\n  if (minutes > 0) {\n    return `${minutes.toString().padStart(2, '0')}:${seconds.toString().padStart(2, '0')}`\n  }\n\n  return `${minutes.toString().padStart(2, '0')}:${seconds.toString().padStart(2, '0')}`\n}\n\nexport const VIDEO_EXTENSIONS = [\n  '.mp4',\n  '.mov',\n  '.avi',\n  '.mkv',\n  '.webm',\n  '.flv',\n  '.wmv',\n  '.mpeg',\n  '.mpg',\n  '.3gp'\n]\n\nexport const AUDIO_EXTENSIONS = ['.mp3', '.wav', '.ogg', '.m4a', '.aac', '.flac', 'm4a']\n\nexport function getType(file: File) {\n  const extension = file.name.split('.').pop()\n  if (extension && VIDEO_EXTENSIONS.includes(extension)) {\n    return 'video'\n  }\n  if (extension && AUDIO_EXTENSIONS.includes(extension)) {\n    return 'audio'\n  }\n  return 'unknown'\n}\n\nexport function formatBitrate(bps: number): string {\n  if (bps >= 1_000_000) {\n    return `${(bps / 1_000_000).toFixed(2)} Mbps`\n  }\n\n  if (bps >= 1_000) {\n    return `${(bps / 1_000).toFixed(0)} kbps`\n  }\n\n  return `${bps.toFixed(0)} bps`\n}\n\nexport function truncateTo2Decimals(num: number): number {\n  return Math.trunc(num * 100) / 100\n}\n",
      "type": "registry:file",
      "target": "@components/media-player/utils.ts"
    }
  ],
  "type": "registry:block"
}
